unfoldedcircle/__init__.py
unfoldedcircle/cli.py
unfoldedcircle/device.py
unfoldedcircle/main.py
python_unfoldedcircle-0.0.2.dist-info/LICENSE.md
python_unfoldedcircle-0.0.2.dist-info/METADATA
python_unfoldedcircle-0.0.2.dist-info/WHEEL
python_unfoldedcircle-0.0.2.dist-info/entry_points.txt
python_unfoldedcircle-0.0.2.dist-info/RECORD
