Metadata-Version: 2.1
Name: python-unfoldedcircle
Version: 0.0.2
Summary: Python library to interact with Unfolde Circle Remote Two
Home-page: https://github.com/mattgruter/python-unfoldedcircle
License: Apache-2.0
Author: Matthias Grüter
Author-email: matthias@grueter.name
Requires-Python: >=3.11,<4.0
Classifier: License :: OSI Approved :: Apache Software License
Classifier: Programming Language :: Python :: 3
Classifier: Programming Language :: Python :: 3.11
Requires-Dist: click (>=8.1.7,<9.0.0)
Requires-Dist: httpx (>=0.25.0,<0.26.0)
Requires-Dist: zeroconf (>=0.119.0,<0.120.0)
Project-URL: Repository, https://github.com/mattgruter/python-unfoldedcircle
